<?xml version="1.0" encoding="utf-8"?>
<Updategram xmlns:i="http://www.w3.org/2001/XMLSchema-instance" xmlns="http://schemas.sportsdataservices.com/integrationService/v3">
	<Header>
		<MessageGuid>7bba1e5f-2348-4b37-9103-4276036f20ac</MessageGuid>
		<TimeStampUtc>2020-12-09T01:45:44.5875553Z</TimeStampUtc>
		<Retry>0</Retry>
		<MessageFixtureOrder>297255511</MessageFixtureOrder>
	</Header>
	<MarketSet>
		<FixtureId>7638505</FixtureId>
		<Markets>
			<Market>
				<Id>107039808</Id>
				<Sequence>0</Sequence>
				<TradingStatus>Open</TradingStatus>
				<Name>1st Half Home Team Totals Over/Under 16.50</Name>
				<ExpiryUtc>2020-12-09T01:05:00Z</ExpiryUtc>
				<Handicap>16.50</Handicap>
				<MarketType>
					<Id>11514</Id>
					<Name>1st Half Home Team Totals Over/Under</Name>
					<IsHandicap>true</IsHandicap>
				</MarketType>
				<InPlay>true</InPlay>
				<Selections>
					<Selection>
						<Id>324547498</Id>
						<TradingStatus>Trading</TradingStatus>
						<Name>Over</Name>
						<Outcome>
							<Id>30</Id>
							<Name>Over</Name>
						</Outcome>
						<Numerator>4</Numerator>
						<Denominator>6</Denominator>
						<Decimal>1.6667</Decimal>
					</Selection>
					<Selection>
						<Id>324547499</Id>
						<TradingStatus>Trading</TradingStatus>
						<Name>Under</Name>
						<Outcome>
							<Id>31</Id>
							<Name>Under</Name>
						</Outcome>
						<Numerator>6</Numerator>
						<Denominator>5</Denominator>
						<Decimal>2.2</Decimal>
					</Selection>
				</Selections>
			</Market>
			<Market>
				<Id>107039351</Id>
				<Sequence>0</Sequence>
				<TradingStatus>Open</TradingStatus>
				<Name>2nd Quarter Home Team Totals Over/Under 9.50</Name>
				<ExpiryUtc>2020-12-09T01:05:00Z</ExpiryUtc>
				<Handicap>9.50</Handicap>
				<MarketType>
					<Id>11643</Id>
					<Name>2nd Quarter Home Team Totals Over/Under</Name>
					<IsHandicap>true</IsHandicap>
				</MarketType>
				<InPlay>true</InPlay>
				<Selections>
					<Selection>
						<Id>324546554</Id>
						<TradingStatus>Trading</TradingStatus>
						<Name>Over</Name>
						<Outcome>
							<Id>30</Id>
							<Name>Over</Name>
						</Outcome>
						<Numerator>4</Numerator>
						<Denominator>6</Denominator>
						<Decimal>1.6667</Decimal>
					</Selection>
					<Selection>
						<Id>324546555</Id>
						<TradingStatus>Trading</TradingStatus>
						<Name>Under</Name>
						<Outcome>
							<Id>31</Id>
							<Name>Under</Name>
						</Outcome>
						<Numerator>6</Numerator>
						<Denominator>5</Denominator>
						<Decimal>2.2</Decimal>
					</Selection>
				</Selections>
			</Market>
		</Markets>
	</MarketSet>
</Updategram>