<?xml version="1.0" encoding="utf-8"?>
<Updategram xmlns:i="http://www.w3.org/2001/XMLSchema-instance" xmlns="http://schemas.sportsdataservices.com/integrationService/v3">
	<Header>
		<MessageGuid>23fa92df-7d8a-423c-be91-f4e0b511ffd4</MessageGuid>
		<TimeStampUtc>2020-12-09T03:57:41.6004456Z</TimeStampUtc>
		<Retry>0</Retry>
		<MessageFixtureOrder>297256143</MessageFixtureOrder>
	</Header>
	<MarketSet>
		<FixtureId>7638505</FixtureId>
		<Markets>
			<Market>
				<Id>107038740</Id>
				<Sequence>0</Sequence>
				<TradingStatus>Suspended</TradingStatus>
				<Name>Home Team Total Points (Odd/Even)</Name>
				<ExpiryUtc>2020-12-09T01:05:00Z</ExpiryUtc>
				<MarketType>
					<Id>10622</Id>
					<Name>Home Team Total Points (Odd/Even)</Name>
					<IsHandicap>false</IsHandicap>
				</MarketType>
				<InPlay>true</InPlay>
				<Selections>
					<Selection>
						<Id>324545313</Id>
						<TradingStatus>Trading</TradingStatus>
						<Name>Odd</Name>
						<Outcome>
							<Id>33</Id>
							<Name>Odd</Name>
						</Outcome>
						<Numerator>8</Numerator>
						<Denominator>1</Denominator>
						<Decimal>9.0</Decimal>
					</Selection>
					<Selection>
						<Id>324545312</Id>
						<TradingStatus>Trading</TradingStatus>
						<Name>Even</Name>
						<Outcome>
							<Id>32</Id>
							<Name>Even</Name>
						</Outcome>
						<Numerator>1</Numerator>
						<Denominator>25</Denominator>
						<Decimal>1.04</Decimal>
					</Selection>
				</Selections>
			</Market>
			<Market>
				<Id>107038753</Id>
				<Sequence>7</Sequence>
				<TradingStatus>Suspended</TradingStatus>
				<Name>Team to Score Seventh Touchdown</Name>
				<ExpiryUtc>2020-12-09T01:05:00Z</ExpiryUtc>
				<MarketType>
					<Id>12860</Id>
					<Name>Team to Score Next Touchdown</Name>
					<IsHandicap>false</IsHandicap>
				</MarketType>
				<InPlay>true</InPlay>
				<Selections>
					<Selection>
						<Id>324545338</Id>
						<TradingStatus>Trading</TradingStatus>
						<Name>Baltimore Ravens</Name>
						<CompetitorId>93331</CompetitorId>
						<Outcome>
							<Id>1</Id>
							<Name>Home</Name>
						</Outcome>
						<Numerator>10</Numerator>
						<Denominator>1</Denominator>
						<Decimal>11.0</Decimal>
					</Selection>
					<Selection>
						<Id>324545339</Id>
						<TradingStatus>Trading</TradingStatus>
						<Name>Dallas Cowboys</Name>
						<CompetitorId>96760</CompetitorId>
						<Outcome>
							<Id>3</Id>
							<Name>Away</Name>
						</Outcome>
						<Numerator>3</Numerator>
						<Denominator>1</Denominator>
						<Decimal>4.0</Decimal>
					</Selection>
					<Selection>
						<Id>324545340</Id>
						<TradingStatus>Trading</TradingStatus>
						<Name>No Touchdown</Name>
						<Outcome>
							<Id>83</Id>
							<Name>No Touchdown</Name>
						</Outcome>
						<Numerator>2</Numerator>
						<Denominator>9</Denominator>
						<Decimal>1.2222</Decimal>
					</Selection>
				</Selections>
			</Market>
		</Markets>
	</MarketSet>
</Updategram>