<?xml version="1.0" encoding="utf-8"?>
<Updategram xmlns:i="http://www.w3.org/2001/XMLSchema-instance" xmlns="http://schemas.sportsdataservices.com/integrationService/v3">
	<Header>
		<MessageGuid>9e829038-615f-4849-90a4-998faa6936ac</MessageGuid>
		<TimeStampUtc>2020-12-07T21:25:17.3825158Z</TimeStampUtc>
		<Retry>0</Retry>
	</Header>
	<MarketSet>
		<FixtureId>7638505</FixtureId>
		<Markets>
			<Market>
				<Id>106837875</Id>
				<TradingStatus>Open</TradingStatus>
				<Name>1st Quarter Total Points</Name>
				<ExpiryUtc>2020-12-09T01:05:00Z</ExpiryUtc>
				<Handicap>7.50</Handicap>
				<MarketType>
					<Id>264</Id>
					<Name>1st Quarter Total Points</Name>
					<IsHandicap>true</IsHandicap>
				</MarketType>
				<InPlay>false</InPlay>
				<Selections>
					<Selection>
						<Id>323949776</Id>
						<TradingStatus>Trading</TradingStatus>
						<Name>Over</Name>
						<Outcome>
							<Id>30</Id>
							<Name>Over</Name>
						</Outcome>
						<Numerator>17</Numerator>
						<Denominator>20</Denominator>
						<Decimal>1.85</Decimal>
					</Selection>
					<Selection>
						<Id>323949777</Id>
						<TradingStatus>Trading</TradingStatus>
						<Name>Under</Name>
						<Outcome>
							<Id>31</Id>
							<Name>Under</Name>
						</Outcome>
						<Numerator>91</Numerator>
						<Denominator>100</Denominator>
						<Decimal>1.91</Decimal>
					</Selection>
				</Selections>
			</Market>
		</Markets>
	</MarketSet>
</Updategram>