<?xml version="1.0" encoding="utf-8"?>
<Updategram xmlns:i="http://www.w3.org/2001/XMLSchema-instance" xmlns="http://schemas.sportsdataservices.com/integrationService/v3">
	<Header>
		<MessageGuid>b6c4cfd4-de41-4205-8393-28b22a2e097e</MessageGuid>
		<TimeStampUtc>2020-12-09T03:39:30.508907Z</TimeStampUtc>
		<Retry>0</Retry>
		<MessageFixtureOrder>297256061</MessageFixtureOrder>
	</Header>
	<MarketSet>
		<FixtureId>7638505</FixtureId>
		<Markets>
			<Market>
				<Id>107038736</Id>
				<Sequence>0</Sequence>
				<TradingStatus>Suspended</TradingStatus>
				<Name>4th Quarter Result</Name>
				<ExpiryUtc>2020-12-09T01:05:00Z</ExpiryUtc>
				<MarketType>
					<Id>9484</Id>
					<Name>4th Quarter Result</Name>
					<IsHandicap>false</IsHandicap>
				</MarketType>
				<InPlay>true</InPlay>
				<Selections>
					<Selection>
						<Id>324545302</Id>
						<TradingStatus>Trading</TradingStatus>
						<Name>Baltimore Ravens</Name>
						<CompetitorId>93331</CompetitorId>
						<Outcome>
							<Id>1</Id>
							<Name>Home</Name>
						</Outcome>
						<Numerator>13</Numerator>
						<Denominator>8</Denominator>
						<Decimal>2.625</Decimal>
					</Selection>
					<Selection>
						<Id>324545303</Id>
						<TradingStatus>Trading</TradingStatus>
						<Name>Draw</Name>
						<Outcome>
							<Id>2</Id>
							<Name>Draw</Name>
						</Outcome>
						<Numerator>15</Numerator>
						<Denominator>2</Denominator>
						<Decimal>8.5</Decimal>
					</Selection>
					<Selection>
						<Id>324545304</Id>
						<TradingStatus>Trading</TradingStatus>
						<Name>Dallas Cowboys</Name>
						<CompetitorId>96760</CompetitorId>
						<Outcome>
							<Id>3</Id>
							<Name>Away</Name>
						</Outcome>
						<Numerator>4</Numerator>
						<Denominator>7</Denominator>
						<Decimal>1.5714</Decimal>
					</Selection>
				</Selections>
			</Market>
		</Markets>
	</MarketSet>
</Updategram>