<?xml version="1.0" encoding="utf-8"?>
<Updategram xmlns:i="http://www.w3.org/2001/XMLSchema-instance" xmlns="http://schemas.sportsdataservices.com/integrationService/v3">
	<Header>
		<MessageGuid>d53ef5f6-2890-404c-92ae-a5dfc0ffeb91</MessageGuid>
		<TimeStampUtc>2020-12-09T02:18:28.4016191Z</TimeStampUtc>
		<Retry>0</Retry>
		<MessageFixtureOrder>297255681</MessageFixtureOrder>
	</Header>
	<MarketSet>
		<FixtureId>7638505</FixtureId>
		<Markets>
			<Market>
				<Id>106517842</Id>
				<Sequence>0</Sequence>
				<TradingStatus>Suspended</TradingStatus>
				<Name>1st Half Result</Name>
				<ExpiryUtc>2020-12-09T01:05:00Z</ExpiryUtc>
				<MarketType>
					<Id>6834</Id>
					<Name>Half-time Result</Name>
					<IsHandicap>false</IsHandicap>
				</MarketType>
				<InPlay>true</InPlay>
				<Selections>
					<Selection>
						<Id>323043779</Id>
						<TradingStatus>Trading</TradingStatus>
						<Name>Baltimore Ravens</Name>
						<CompetitorId>93331</CompetitorId>
						<Outcome>
							<Id>1</Id>
							<Name>Home</Name>
						</Outcome>
						<Numerator>1</Numerator>
						<Denominator>100</Denominator>
						<Decimal>1.01</Decimal>
					</Selection>
					<Selection>
						<Id>323043780</Id>
						<TradingStatus>Trading</TradingStatus>
						<Name>Draw</Name>
						<Outcome>
							<Id>2</Id>
							<Name>Draw</Name>
						</Outcome>
						<Numerator>8</Numerator>
						<Denominator>1</Denominator>
						<Decimal>9.0</Decimal>
					</Selection>
					<Selection>
						<Id>323043781</Id>
						<TradingStatus>Trading</TradingStatus>
						<Name>Dallas Cowboys</Name>
						<CompetitorId>96760</CompetitorId>
						<Outcome>
							<Id>3</Id>
							<Name>Away</Name>
						</Outcome>
						<Numerator>33</Numerator>
						<Denominator>1</Denominator>
						<Decimal>34.0</Decimal>
					</Selection>
				</Selections>
			</Market>
			<Market>
				<Id>107038737</Id>
				<Sequence>0</Sequence>
				<TradingStatus>Suspended</TradingStatus>
				<Name>2nd Half Result</Name>
				<ExpiryUtc>2020-12-09T01:05:00Z</ExpiryUtc>
				<MarketType>
					<Id>10042</Id>
					<Name>2nd Half Result</Name>
					<IsHandicap>false</IsHandicap>
				</MarketType>
				<InPlay>true</InPlay>
				<Selections>
					<Selection>
						<Id>324545305</Id>
						<TradingStatus>Trading</TradingStatus>
						<Name>Baltimore Ravens</Name>
						<CompetitorId>93331</CompetitorId>
						<Outcome>
							<Id>1</Id>
							<Name>Home</Name>
						</Outcome>
						<Numerator>4</Numerator>
						<Denominator>7</Denominator>
						<Decimal>1.5714</Decimal>
					</Selection>
					<Selection>
						<Id>324545306</Id>
						<TradingStatus>Trading</TradingStatus>
						<Name>Draw</Name>
						<Outcome>
							<Id>2</Id>
							<Name>Draw</Name>
						</Outcome>
						<Numerator>15</Numerator>
						<Denominator>2</Denominator>
						<Decimal>8.5</Decimal>
					</Selection>
					<Selection>
						<Id>324545307</Id>
						<TradingStatus>Trading</TradingStatus>
						<Name>Dallas Cowboys</Name>
						<CompetitorId>96760</CompetitorId>
						<Outcome>
							<Id>3</Id>
							<Name>Away</Name>
						</Outcome>
						<Numerator>13</Numerator>
						<Denominator>8</Denominator>
						<Decimal>2.625</Decimal>
					</Selection>
				</Selections>
			</Market>
			<Market>
				<Id>107039755</Id>
				<Sequence>0</Sequence>
				<TradingStatus>Suspended</TradingStatus>
				<Name>Home Team Total Points Over/Under 30.50</Name>
				<ExpiryUtc>2020-12-09T01:05:00Z</ExpiryUtc>
				<Handicap>30.50</Handicap>
				<MarketType>
					<Id>8252</Id>
					<Name>Home Team Total Points Over/Under</Name>
					<IsHandicap>true</IsHandicap>
				</MarketType>
				<InPlay>true</InPlay>
				<Selections>
					<Selection>
						<Id>324547385</Id>
						<TradingStatus>Trading</TradingStatus>
						<Name>Over</Name>
						<Outcome>
							<Id>30</Id>
							<Name>Over</Name>
						</Outcome>
						<Numerator>9</Numerator>
						<Denominator>10</Denominator>
						<Decimal>1.9</Decimal>
					</Selection>
					<Selection>
						<Id>324547386</Id>
						<TradingStatus>Trading</TradingStatus>
						<Name>Under</Name>
						<Outcome>
							<Id>31</Id>
							<Name>Under</Name>
						</Outcome>
						<Numerator>9</Numerator>
						<Denominator>10</Denominator>
						<Decimal>1.9</Decimal>
					</Selection>
				</Selections>
			</Market>
			<Market>
				<Id>107038753</Id>
				<Sequence>4</Sequence>
				<TradingStatus>Suspended</TradingStatus>
				<Name>Team to Score Fourth Touchdown</Name>
				<ExpiryUtc>2020-12-09T01:05:00Z</ExpiryUtc>
				<MarketType>
					<Id>12860</Id>
					<Name>Team to Score Next Touchdown</Name>
					<IsHandicap>false</IsHandicap>
				</MarketType>
				<InPlay>true</InPlay>
				<Selections>
					<Selection>
						<Id>324545338</Id>
						<TradingStatus>Trading</TradingStatus>
						<Name>Baltimore Ravens</Name>
						<CompetitorId>93331</CompetitorId>
						<Outcome>
							<Id>1</Id>
							<Name>Home</Name>
						</Outcome>
						<Numerator>2</Numerator>
						<Denominator>5</Denominator>
						<Decimal>1.4</Decimal>
					</Selection>
					<Selection>
						<Id>324545339</Id>
						<TradingStatus>Trading</TradingStatus>
						<Name>Dallas Cowboys</Name>
						<CompetitorId>96760</CompetitorId>
						<Outcome>
							<Id>3</Id>
							<Name>Away</Name>
						</Outcome>
						<Numerator>7</Numerator>
						<Denominator>5</Denominator>
						<Decimal>2.4</Decimal>
					</Selection>
					<Selection>
						<Id>324545340</Id>
						<TradingStatus>Trading</TradingStatus>
						<Name>No Touchdown</Name>
						<Outcome>
							<Id>83</Id>
							<Name>No Touchdown</Name>
						</Outcome>
						<Numerator>40</Numerator>
						<Denominator>1</Denominator>
						<Decimal>41.0</Decimal>
					</Selection>
				</Selections>
			</Market>
			<Market>
				<Id>106430752</Id>
				<Sequence>0</Sequence>
				<TradingStatus>Suspended</TradingStatus>
				<Name>Win Match Normal Time</Name>
				<ExpiryUtc>2020-12-09T01:05:00Z</ExpiryUtc>
				<MarketType>
					<Id>6571</Id>
					<Name>Match Result</Name>
					<IsHandicap>false</IsHandicap>
				</MarketType>
				<InPlay>true</InPlay>
				<Selections>
					<Selection>
						<Id>322771222</Id>
						<TradingStatus>Trading</TradingStatus>
						<Name>Baltimore Ravens</Name>
						<CompetitorId>93331</CompetitorId>
						<Outcome>
							<Id>1</Id>
							<Name>Home</Name>
						</Outcome>
						<Numerator>1</Numerator>
						<Denominator>7</Denominator>
						<Decimal>1.1429</Decimal>
					</Selection>
					<Selection>
						<Id>322771223</Id>
						<TradingStatus>Trading</TradingStatus>
						<Name>Draw</Name>
						<Outcome>
							<Id>2</Id>
							<Name>Draw</Name>
						</Outcome>
						<Numerator>11</Numerator>
						<Denominator>1</Denominator>
						<Decimal>12.0</Decimal>
					</Selection>
					<Selection>
						<Id>322771224</Id>
						<TradingStatus>Trading</TradingStatus>
						<Name>Dallas Cowboys</Name>
						<CompetitorId>96760</CompetitorId>
						<Outcome>
							<Id>3</Id>
							<Name>Away</Name>
						</Outcome>
						<Numerator>11</Numerator>
						<Denominator>2</Denominator>
						<Decimal>6.5</Decimal>
					</Selection>
				</Selections>
			</Market>
		</Markets>
	</MarketSet>
</Updategram>