<?xml version="1.0" encoding="utf-8"?>
<Updategram xmlns:i="http://www.w3.org/2001/XMLSchema-instance" xmlns="http://schemas.sportsdataservices.com/integrationService/v3">
	<Header>
		<MessageGuid>fd526113-aa61-4bf2-a470-3d70133df966</MessageGuid>
		<TimeStampUtc>2020-12-08T16:05:24.6219204Z</TimeStampUtc>
		<Retry>0</Retry>
	</Header>
	<MarketSet>
		<FixtureId>7638505</FixtureId>
		<Markets>
			<Market>
				<Id>106517840</Id>
				<TradingStatus>Open</TradingStatus>
				<Name>4th Quarter Money Line</Name>
				<ExpiryUtc>2020-12-09T01:05:00Z</ExpiryUtc>
				<MarketType>
					<Id>6808</Id>
					<Name>4th Quarter Money Line</Name>
					<IsHandicap>false</IsHandicap>
				</MarketType>
				<InPlay>false</InPlay>
				<Selections>
					<Selection>
						<Id>323043775</Id>
						<TradingStatus>Trading</TradingStatus>
						<Name>Baltimore Ravens</Name>
						<CompetitorId>93331</CompetitorId>
						<Outcome>
							<Id>1</Id>
							<Name>Home</Name>
						</Outcome>
						<Numerator>11</Numerator>
						<Denominator>20</Denominator>
						<Decimal>1.55</Decimal>
					</Selection>
					<Selection>
						<Id>323043776</Id>
						<TradingStatus>Trading</TradingStatus>
						<Name>Dallas Cowboys</Name>
						<CompetitorId>96760</CompetitorId>
						<Outcome>
							<Id>3</Id>
							<Name>Away</Name>
						</Outcome>
						<Numerator>69</Numerator>
						<Denominator>50</Denominator>
						<Decimal>2.38</Decimal>
					</Selection>
				</Selections>
			</Market>
		</Markets>
	</MarketSet>
</Updategram>