<?xml version="1.0" encoding="utf-8"?>
<Updategram xmlns:i="http://www.w3.org/2001/XMLSchema-instance" xmlns="http://schemas.sportsdataservices.com/integrationService/v3">
	<Header>
		<MessageGuid>3e869377-a536-4cff-8597-bb28ee6c5f9a</MessageGuid>
		<TimeStampUtc>2016-07-02T15:23:20.613561Z</TimeStampUtc>
		<Retry>0</Retry>
	</Header>
	<MarketSet>
		<FixtureId>4046194</FixtureId>
		<Markets>
			<Market>
				<Id>100654428</Id>
				<TradingStatus>Open</TradingStatus>
				<Name>Over/Under</Name>
				<ExpiryUtc>2016-07-02T19:00:00</ExpiryUtc>
				<Handicap>3.50</Handicap>
				<MarketType>
					<Id>259</Id>
					<Name>Over/Under</Name>
					<IsHandicap>true</IsHandicap>
				</MarketType>
				<InPlay>false</InPlay>
				<Selections>
					<Selection>
						<Id>302268616</Id>
						<TradingStatus>Trading</TradingStatus>
						<Name>Over</Name>
						<Outcome>
							<Id>30</Id>
							<Name>Over</Name>
						</Outcome>
						<Numerator>4</Numerator>
						<Denominator>1</Denominator>
						<Decimal>5</Decimal>
					</Selection>
					<Selection>
						<Id>302268617</Id>
						<TradingStatus>Trading</TradingStatus>
						<Name>Under</Name>
						<Outcome>
							<Id>31</Id>
							<Name>Under</Name>
						</Outcome>
						<Numerator>9</Numerator>
						<Denominator>50</Denominator>
						<Decimal>1.18</Decimal>
					</Selection>
				</Selections>
			</Market>
		</Markets>
	</MarketSet>
</Updategram>