<?xml version="1.0" encoding="utf-8"?>
<Updategram xmlns:i="http://www.w3.org/2001/XMLSchema-instance" xmlns="http://schemas.sportsdataservices.com/integrationService/v3">
	<Header>
		<MessageGuid>c3258fb1-0cee-4248-9b64-c4658fc1a905</MessageGuid>
		<TimeStampUtc>2016-07-02T21:32:42.8449157Z</TimeStampUtc>
		<Retry>0</Retry>
	</Header>
	<ResultSet>
		<FixtureId>4046194</FixtureId>
		<Results>
			<MarketResult>
				<MarketId>100711143</MarketId>
				<MarketSequence>0</MarketSequence>
				<Results>
					<SelectionResult>
						<SelectionId>302511569</SelectionId>
						<ResultStatus>Loser</ResultStatus>
					</SelectionResult>
					<SelectionResult>
						<SelectionId>302511570</SelectionId>
						<ResultStatus>Winner</ResultStatus>
					</SelectionResult>
				</Results>
			</MarketResult>
		</Results>
	</ResultSet>
</Updategram>