<?xml version="1.0" encoding="utf-8"?>
<Updategram xmlns:i="http://www.w3.org/2001/XMLSchema-instance" xmlns="http://schemas.sportsdataservices.com/integrationService/v3">
	<Header>
		<MessageGuid>c3aa3d33-e658-463e-8b19-7b432e7feaf9</MessageGuid>
		<TimeStampUtc>2016-06-27T18:15:33.2623546Z</TimeStampUtc>
		<Retry>0</Retry>
	</Header>
	<MarketSet>
		<FixtureId>4046194</FixtureId>
		<Markets>
			<Market>
				<Id>100654074</Id>
				<TradingStatus>Open</TradingStatus>
				<Name>Double Chance</Name>
				<ExpiryUtc>2016-07-02T19:00:00</ExpiryUtc>
				<MarketType>
					<Id>7202</Id>
					<Name>Double Chance</Name>
					<IsHandicap>false</IsHandicap>
				</MarketType>
				<InPlay>false</InPlay>
				<Selections>
					<Selection>
						<Id>302267272</Id>
						<TradingStatus>Trading</TradingStatus>
						<Name>Germany or Draw</Name>
						<Outcome>
							<Id>7</Id>
							<Name>Home or Draw</Name>
						</Outcome>
						<Numerator>2</Numerator>
						<Denominator>11</Denominator>
						<Decimal>1.18181818181818</Decimal>
					</Selection>
					<Selection>
						<Id>302267273</Id>
						<TradingStatus>Trading</TradingStatus>
						<Name>Germany or Italy</Name>
						<Outcome>
							<Id>8</Id>
							<Name>Home or Away</Name>
						</Outcome>
						<Numerator>3</Numerator>
						<Denominator>10</Denominator>
						<Decimal>1.3</Decimal>
					</Selection>
					<Selection>
						<Id>302267274</Id>
						<TradingStatus>Trading</TradingStatus>
						<Name>Draw or Italy</Name>
						<Outcome>
							<Id>9</Id>
							<Name>Draw or Away</Name>
						</Outcome>
						<Numerator>8</Numerator>
						<Denominator>13</Denominator>
						<Decimal>1.61538461538462</Decimal>
					</Selection>
				</Selections>
			</Market>
		</Markets>
	</MarketSet>
</Updategram>