<?xml version="1.0" encoding="utf-8"?>
<Updategram xmlns:i="http://www.w3.org/2001/XMLSchema-instance" xmlns="http://schemas.sportsdataservices.com/integrationService/v3">
	<Header>
		<MessageGuid>59ca6d96-f020-49b6-ba3b-ab46e0ec40c4</MessageGuid>
		<TimeStampUtc>2016-07-06T13:29:47.207095Z</TimeStampUtc>
		<Retry>0</Retry>
	</Header>
	<ResultSet>
		<FixtureId>3221673</FixtureId>
		<Results>
			<MarketResult>
				<MarketId>100747585</MarketId>
				<MarketSequence>4002003</MarketSequence>
				<Results>
					<SelectionResult>
						<SelectionId>302667322</SelectionId>
						<ResultStatus>Loser</ResultStatus>
					</SelectionResult>
					<SelectionResult>
						<SelectionId>302667323</SelectionId>
						<ResultStatus>Winner</ResultStatus>
					</SelectionResult>
				</Results>
			</MarketResult>
		</Results>
	</ResultSet>
</Updategram>