<?xml version="1.0" encoding="utf-8"?>
<Updategram xmlns:i="http://www.w3.org/2001/XMLSchema-instance" xmlns="http://schemas.sportsdataservices.com/integrationService/v3">
	<Header>
		<MessageGuid>388f9428-34c0-4e92-a817-1a2bb1dc72d4</MessageGuid>
		<TimeStampUtc>2016-07-06T18:44:14.4963056Z</TimeStampUtc>
		<Retry>0</Retry>
	</Header>
	<ResultSet>
		<FixtureId>4048000</FixtureId>
		<Results>
			<MarketResult>
				<MarketId>100413391</MarketId>
				<MarketSequence>0</MarketSequence>
				<Results>
					<SelectionResult>
						<SelectionId>301140475</SelectionId>
						<ResultStatus>Winner</ResultStatus>
					</SelectionResult>
					<SelectionResult>
						<SelectionId>301140476</SelectionId>
						<ResultStatus>Loser</ResultStatus>
					</SelectionResult>
				</Results>
			</MarketResult>
		</Results>
	</ResultSet>
</Updategram>