<?xml version="1.0" encoding="utf-8"?>
<Updategram xmlns:i="http://www.w3.org/2001/XMLSchema-instance" xmlns="http://schemas.sportsdataservices.com/integrationService/v3">
	<Header>
		<MessageGuid>c969b8cb-ccf5-4084-a53c-e512b3d42d20</MessageGuid>
		<TimeStampUtc>2016-07-06T17:28:59.3340847Z</TimeStampUtc>
		<Retry>0</Retry>
		<MessageFixtureOrder>163044163</MessageFixtureOrder>
	</Header>
	<MarketSet>
		<FixtureId>4048000</FixtureId>
		<Markets>
			<Market>
				<Id>100413197</Id>
				<Sequence>0</Sequence>
				<TradingStatus>Open</TradingStatus>
				<Name>Point Spread -8.50</Name>
				<ExpiryUtc>2016-07-06T17:00:00Z</ExpiryUtc>
				<Handicap>-8.5</Handicap>
				<MarketType>
					<Id>147</Id>
					<Name>Point Spread</Name>
					<IsHandicap>true</IsHandicap>
				</MarketType>
				<InPlay>true</InPlay>
				<Selections>
					<Selection>
						<Id>301140062</Id>
						<TradingStatus>Trading</TradingStatus>
						<Name>New York Knicks</Name>
						<CompetitorId>134847</CompetitorId>
						<Outcome>
							<Id>4</Id>
							<Name>Home</Name>
						</Outcome>
						<Numerator>91</Numerator>
						<Denominator>100</Denominator>
						<Decimal>1.91</Decimal>
					</Selection>
					<Selection>
						<Id>301140063</Id>
						<TradingStatus>Trading</TradingStatus>
						<Name>Orlando White</Name>
						<CompetitorId>825504</CompetitorId>
						<Outcome>
							<Id>5</Id>
							<Name>Away</Name>
						</Outcome>
						<Numerator>47</Numerator>
						<Denominator>50</Denominator>
						<Decimal>1.94</Decimal>
					</Selection>
				</Selections>
			</Market>
			<Market>
				<Id>100413378</Id>
				<Sequence>0</Sequence>
				<TradingStatus>Open</TradingStatus>
				<Name>Total Points Over / Under 157.50</Name>
				<ExpiryUtc>2016-07-06T17:00:00Z</ExpiryUtc>
				<Handicap>157.5</Handicap>
				<MarketType>
					<Id>286</Id>
					<Name>Total Points Over/Under</Name>
					<IsHandicap>true</IsHandicap>
				</MarketType>
				<InPlay>true</InPlay>
				<Selections>
					<Selection>
						<Id>301140449</Id>
						<TradingStatus>Trading</TradingStatus>
						<Name>Over</Name>
						<Outcome>
							<Id>30</Id>
							<Name>Over</Name>
						</Outcome>
						<Numerator>24</Numerator>
						<Denominator>25</Denominator>
						<Decimal>1.96</Decimal>
					</Selection>
					<Selection>
						<Id>301140450</Id>
						<TradingStatus>Trading</TradingStatus>
						<Name>Under</Name>
						<Outcome>
							<Id>31</Id>
							<Name>Under</Name>
						</Outcome>
						<Numerator>89</Numerator>
						<Denominator>100</Denominator>
						<Decimal>1.89</Decimal>
					</Selection>
				</Selections>
			</Market>
			<Market>
				<Id>100413353</Id>
				<Sequence>0</Sequence>
				<TradingStatus>Open</TradingStatus>
				<Name>1st Half Total Points Over/Under 79.50</Name>
				<ExpiryUtc>2016-07-06T17:00:00Z</ExpiryUtc>
				<Handicap>79.5</Handicap>
				<MarketType>
					<Id>6698</Id>
					<Name>1st Half Total Points Over/Under</Name>
					<IsHandicap>true</IsHandicap>
				</MarketType>
				<InPlay>true</InPlay>
				<Selections>
					<Selection>
						<Id>301140399</Id>
						<TradingStatus>Trading</TradingStatus>
						<Name>Over</Name>
						<Outcome>
							<Id>30</Id>
							<Name>Over</Name>
						</Outcome>
						<Numerator>17</Numerator>
						<Denominator>20</Denominator>
						<Decimal>1.85</Decimal>
					</Selection>
					<Selection>
						<Id>301140400</Id>
						<TradingStatus>Trading</TradingStatus>
						<Name>Under</Name>
						<Outcome>
							<Id>31</Id>
							<Name>Under</Name>
						</Outcome>
						<Numerator>1</Numerator>
						<Denominator>1</Denominator>
						<Decimal>2.0</Decimal>
					</Selection>
				</Selections>
			</Market>
			<Market>
				<Id>100413489</Id>
				<Sequence>0</Sequence>
				<TradingStatus>Open</TradingStatus>
				<Name>2nd Quarter Total Points Over/Under 36.50</Name>
				<ExpiryUtc>2016-07-06T17:00:00Z</ExpiryUtc>
				<Handicap>36.5</Handicap>
				<MarketType>
					<Id>6851</Id>
					<Name>2nd Quarter Total Points Over/Under</Name>
					<IsHandicap>true</IsHandicap>
				</MarketType>
				<InPlay>true</InPlay>
				<Selections>
					<Selection>
						<Id>301140671</Id>
						<TradingStatus>Trading</TradingStatus>
						<Name>Over</Name>
						<Outcome>
							<Id>30</Id>
							<Name>Over</Name>
						</Outcome>
						<Numerator>17</Numerator>
						<Denominator>20</Denominator>
						<Decimal>1.85</Decimal>
					</Selection>
					<Selection>
						<Id>301140672</Id>
						<TradingStatus>Trading</TradingStatus>
						<Name>Under</Name>
						<Outcome>
							<Id>31</Id>
							<Name>Under</Name>
						</Outcome>
						<Numerator>1</Numerator>
						<Denominator>1</Denominator>
						<Decimal>2.0</Decimal>
					</Selection>
				</Selections>
			</Market>
			<Market>
				<Id>100413549</Id>
				<Sequence>0</Sequence>
				<TradingStatus>Open</TradingStatus>
				<Name>3rd Quarter Total Points Over/Under 37.50</Name>
				<ExpiryUtc>2016-07-06T17:00:00Z</ExpiryUtc>
				<Handicap>37.5</Handicap>
				<MarketType>
					<Id>6852</Id>
					<Name>3rd Quarter Total Points Over/Under</Name>
					<IsHandicap>true</IsHandicap>
				</MarketType>
				<InPlay>true</InPlay>
				<Selections>
					<Selection>
						<Id>301140796</Id>
						<TradingStatus>Trading</TradingStatus>
						<Name>Over</Name>
						<Outcome>
							<Id>30</Id>
							<Name>Over</Name>
						</Outcome>
						<Numerator>89</Numerator>
						<Denominator>100</Denominator>
						<Decimal>1.89</Decimal>
					</Selection>
					<Selection>
						<Id>301140797</Id>
						<TradingStatus>Trading</TradingStatus>
						<Name>Under</Name>
						<Outcome>
							<Id>31</Id>
							<Name>Under</Name>
						</Outcome>
						<Numerator>24</Numerator>
						<Denominator>25</Denominator>
						<Decimal>1.96</Decimal>
					</Selection>
				</Selections>
			</Market>
			<Market>
				<Id>100413213</Id>
				<Sequence>0</Sequence>
				<TradingStatus>Open</TradingStatus>
				<Name>2nd Half Point Spread -3.50</Name>
				<ExpiryUtc>2016-07-06T17:00:00Z</ExpiryUtc>
				<Handicap>-3.5</Handicap>
				<MarketType>
					<Id>7416</Id>
					<Name>2nd Half Point Spread</Name>
					<IsHandicap>true</IsHandicap>
				</MarketType>
				<InPlay>true</InPlay>
				<Selections>
					<Selection>
						<Id>301140096</Id>
						<TradingStatus>Trading</TradingStatus>
						<Name>New York Knicks</Name>
						<CompetitorId>134847</CompetitorId>
						<Outcome>
							<Id>4</Id>
							<Name>Home</Name>
						</Outcome>
						<Numerator>91</Numerator>
						<Denominator>100</Denominator>
						<Decimal>1.91</Decimal>
					</Selection>
					<Selection>
						<Id>301140097</Id>
						<TradingStatus>Trading</TradingStatus>
						<Name>Orlando White</Name>
						<CompetitorId>825504</CompetitorId>
						<Outcome>
							<Id>5</Id>
							<Name>Away</Name>
						</Outcome>
						<Numerator>47</Numerator>
						<Denominator>50</Denominator>
						<Decimal>1.94</Decimal>
					</Selection>
				</Selections>
			</Market>
			<Market>
				<Id>100413399</Id>
				<Sequence>0</Sequence>
				<TradingStatus>Open</TradingStatus>
				<Name>2nd Half Total Points Over/Under 75.50</Name>
				<ExpiryUtc>2016-07-06T17:00:00Z</ExpiryUtc>
				<Handicap>75.5</Handicap>
				<MarketType>
					<Id>7417</Id>
					<Name>2nd Half Total Points Over/Under</Name>
					<IsHandicap>true</IsHandicap>
				</MarketType>
				<InPlay>true</InPlay>
				<Selections>
					<Selection>
						<Id>301140491</Id>
						<TradingStatus>Trading</TradingStatus>
						<Name>Over</Name>
						<Outcome>
							<Id>30</Id>
							<Name>Over</Name>
						</Outcome>
						<Numerator>87</Numerator>
						<Denominator>100</Denominator>
						<Decimal>1.87</Decimal>
					</Selection>
					<Selection>
						<Id>301140492</Id>
						<TradingStatus>Trading</TradingStatus>
						<Name>Under</Name>
						<Outcome>
							<Id>31</Id>
							<Name>Under</Name>
						</Outcome>
						<Numerator>49</Numerator>
						<Denominator>50</Denominator>
						<Decimal>1.98</Decimal>
					</Selection>
				</Selections>
			</Market>
			<Market>
				<Id>100413357</Id>
				<Sequence>0</Sequence>
				<TradingStatus>Open</TradingStatus>
				<Name>Home Team Points Over/Under 74.50</Name>
				<ExpiryUtc>2016-07-06T17:00:00Z</ExpiryUtc>
				<Handicap>74.5</Handicap>
				<MarketType>
					<Id>8421</Id>
					<Name>Home Team Points Over/Under</Name>
					<IsHandicap>true</IsHandicap>
				</MarketType>
				<InPlay>true</InPlay>
				<Selections>
					<Selection>
						<Id>301140407</Id>
						<TradingStatus>Trading</TradingStatus>
						<Name>Over</Name>
						<Outcome>
							<Id>30</Id>
							<Name>Over</Name>
						</Outcome>
						<Numerator>47</Numerator>
						<Denominator>50</Denominator>
						<Decimal>1.94</Decimal>
					</Selection>
					<Selection>
						<Id>301140408</Id>
						<TradingStatus>Trading</TradingStatus>
						<Name>Under</Name>
						<Outcome>
							<Id>31</Id>
							<Name>Under</Name>
						</Outcome>
						<Numerator>91</Numerator>
						<Denominator>100</Denominator>
						<Decimal>1.91</Decimal>
					</Selection>
				</Selections>
			</Market>
			<Market>
				<Id>100413391</Id>
				<Sequence>0</Sequence>
				<TradingStatus>Open</TradingStatus>
				<Name>Away Team Points Over/Under 82.50</Name>
				<ExpiryUtc>2016-07-06T17:00:00Z</ExpiryUtc>
				<Handicap>82.5</Handicap>
				<MarketType>
					<Id>8422</Id>
					<Name>Away Team Points Over/Under</Name>
					<IsHandicap>true</IsHandicap>
				</MarketType>
				<InPlay>true</InPlay>
				<Selections>
					<Selection>
						<Id>301140475</Id>
						<TradingStatus>Trading</TradingStatus>
						<Name>Over</Name>
						<Outcome>
							<Id>30</Id>
							<Name>Over</Name>
						</Outcome>
						<Numerator>87</Numerator>
						<Denominator>100</Denominator>
						<Decimal>1.87</Decimal>
					</Selection>
					<Selection>
						<Id>301140476</Id>
						<TradingStatus>Trading</TradingStatus>
						<Name>Under</Name>
						<Outcome>
							<Id>31</Id>
							<Name>Under</Name>
						</Outcome>
						<Numerator>49</Numerator>
						<Denominator>50</Denominator>
						<Decimal>1.98</Decimal>
					</Selection>
				</Selections>
			</Market>
			<Market>
				<Id>100413223</Id>
				<Sequence>0</Sequence>
				<TradingStatus>Open</TradingStatus>
				<Name>2nd Quarter Race To 10 Points</Name>
				<ExpiryUtc>2016-07-06T17:00:00Z</ExpiryUtc>
				<MarketType>
					<Id>10505</Id>
					<Name>2nd Quarter Race To 10 Points</Name>
					<IsHandicap>false</IsHandicap>
				</MarketType>
				<InPlay>true</InPlay>
				<Selections>
					<Selection>
						<Id>301140118</Id>
						<TradingStatus>Trading</TradingStatus>
						<Name>New York Knicks</Name>
						<CompetitorId>134847</CompetitorId>
						<Outcome>
							<Id>1</Id>
							<Name>Home</Name>
						</Outcome>
						<Numerator>11</Numerator>
						<Denominator>10</Denominator>
						<Decimal>2.1</Decimal>
					</Selection>
					<Selection>
						<Id>301140120</Id>
						<TradingStatus>Trading</TradingStatus>
						<Name>Orlando White</Name>
						<CompetitorId>825504</CompetitorId>
						<Outcome>
							<Id>3</Id>
							<Name>Away</Name>
						</Outcome>
						<Numerator>3</Numerator>
						<Denominator>5</Denominator>
						<Decimal>1.6</Decimal>
					</Selection>
					<Selection>
						<Id>301140119</Id>
						<TradingStatus>Trading</TradingStatus>
						<Name>Neither</Name>
						<Outcome>
							<Id>2</Id>
							<Name>Neither</Name>
						</Outcome>
						<Numerator>100</Numerator>
						<Denominator>1</Denominator>
						<Decimal>101.0</Decimal>
					</Selection>
				</Selections>
			</Market>
			<Market>
				<Id>100413230</Id>
				<Sequence>0</Sequence>
				<TradingStatus>Open</TradingStatus>
				<Name>2nd Quarter Race To 20 Points</Name>
				<ExpiryUtc>2016-07-06T17:00:00Z</ExpiryUtc>
				<MarketType>
					<Id>11750</Id>
					<Name>2nd Quarter Race To 20 Points</Name>
					<IsHandicap>false</IsHandicap>
				</MarketType>
				<InPlay>true</InPlay>
				<Selections>
					<Selection>
						<Id>301140139</Id>
						<TradingStatus>Trading</TradingStatus>
						<Name>New York Knicks</Name>
						<CompetitorId>134847</CompetitorId>
						<Outcome>
							<Id>1</Id>
							<Name>Home</Name>
						</Outcome>
						<Numerator>13</Numerator>
						<Denominator>5</Denominator>
						<Decimal>3.6</Decimal>
					</Selection>
					<Selection>
						<Id>301140141</Id>
						<TradingStatus>Trading</TradingStatus>
						<Name>Orlando White</Name>
						<CompetitorId>825504</CompetitorId>
						<Outcome>
							<Id>3</Id>
							<Name>Away</Name>
						</Outcome>
						<Numerator>13</Numerator>
						<Denominator>10</Denominator>
						<Decimal>2.3</Decimal>
					</Selection>
					<Selection>
						<Id>301140140</Id>
						<TradingStatus>Trading</TradingStatus>
						<Name>Neither</Name>
						<Outcome>
							<Id>2</Id>
							<Name>Neither</Name>
						</Outcome>
						<Numerator>6</Numerator>
						<Denominator>4</Denominator>
						<Decimal>2.5</Decimal>
					</Selection>
				</Selections>
			</Market>
			<Market>
				<Id>100413546</Id>
				<Sequence>0</Sequence>
				<TradingStatus>Open</TradingStatus>
				<Name>3rd Quarter Race To 15 Points</Name>
				<ExpiryUtc>2016-07-06T17:00:00Z</ExpiryUtc>
				<MarketType>
					<Id>11753</Id>
					<Name>3rd Quarter Race To 15 Points</Name>
					<IsHandicap>false</IsHandicap>
				</MarketType>
				<InPlay>true</InPlay>
				<Selections>
					<Selection>
						<Id>301140788</Id>
						<TradingStatus>Trading</TradingStatus>
						<Name>New York Knicks</Name>
						<CompetitorId>134847</CompetitorId>
						<Outcome>
							<Id>1</Id>
							<Name>Home</Name>
						</Outcome>
						<Numerator>11</Numerator>
						<Denominator>8</Denominator>
						<Decimal>2.375</Decimal>
					</Selection>
					<Selection>
						<Id>301140790</Id>
						<TradingStatus>Trading</TradingStatus>
						<Name>Orlando White</Name>
						<CompetitorId>825504</CompetitorId>
						<Outcome>
							<Id>3</Id>
							<Name>Away</Name>
						</Outcome>
						<Numerator>8</Numerator>
						<Denominator>13</Denominator>
						<Decimal>1.6154</Decimal>
					</Selection>
					<Selection>
						<Id>301140789</Id>
						<TradingStatus>Trading</TradingStatus>
						<Name>Neither</Name>
						<Outcome>
							<Id>2</Id>
							<Name>Neither</Name>
						</Outcome>
						<Numerator>12</Numerator>
						<Denominator>1</Denominator>
						<Decimal>13.0</Decimal>
					</Selection>
				</Selections>
			</Market>
			<Market>
				<Id>100413547</Id>
				<Sequence>0</Sequence>
				<TradingStatus>Open</TradingStatus>
				<Name>3rd Quarter Race To 20 Points</Name>
				<ExpiryUtc>2016-07-06T17:00:00Z</ExpiryUtc>
				<MarketType>
					<Id>11754</Id>
					<Name>3rd Quarter Race To 20 Points</Name>
					<IsHandicap>false</IsHandicap>
				</MarketType>
				<InPlay>true</InPlay>
				<Selections>
					<Selection>
						<Id>301140791</Id>
						<TradingStatus>Trading</TradingStatus>
						<Name>New York Knicks</Name>
						<CompetitorId>134847</CompetitorId>
						<Outcome>
							<Id>1</Id>
							<Name>Home</Name>
						</Outcome>
						<Numerator>5</Numerator>
						<Denominator>2</Denominator>
						<Decimal>3.5</Decimal>
					</Selection>
					<Selection>
						<Id>301140793</Id>
						<TradingStatus>Trading</TradingStatus>
						<Name>Orlando White</Name>
						<CompetitorId>825504</CompetitorId>
						<Outcome>
							<Id>3</Id>
							<Name>Away</Name>
						</Outcome>
						<Numerator>6</Numerator>
						<Denominator>5</Denominator>
						<Decimal>2.2</Decimal>
					</Selection>
					<Selection>
						<Id>301140792</Id>
						<TradingStatus>Trading</TradingStatus>
						<Name>Neither</Name>
						<Outcome>
							<Id>2</Id>
							<Name>Neither</Name>
						</Outcome>
						<Numerator>13</Numerator>
						<Denominator>8</Denominator>
						<Decimal>2.625</Decimal>
					</Selection>
				</Selections>
			</Market>
			<Market>
				<Id>100413362</Id>
				<Sequence>0</Sequence>
				<TradingStatus>Closed</TradingStatus>
				<Name>Total Points Over / Under 155.50</Name>
				<ExpiryUtc>2016-07-06T17:00:00</ExpiryUtc>
				<Handicap>155.50</Handicap>
				<MarketType>
					<Id>286</Id>
					<Name>Total Points Over/Under</Name>
					<IsHandicap>true</IsHandicap>
				</MarketType>
				<InPlay>true</InPlay>
				<Selections>
					<Selection>
						<Id>301140417</Id>
						<TradingStatus>Suspended</TradingStatus>
						<Name>Over</Name>
						<Outcome>
							<Id>30</Id>
							<Name>Over</Name>
						</Outcome>
						<Numerator>0</Numerator>
						<Denominator>1</Denominator>
						<Decimal>1.0</Decimal>
					</Selection>
					<Selection>
						<Id>301140418</Id>
						<TradingStatus>Suspended</TradingStatus>
						<Name>Under</Name>
						<Outcome>
							<Id>31</Id>
							<Name>Under</Name>
						</Outcome>
						<Numerator>0</Numerator>
						<Denominator>1</Denominator>
						<Decimal>1.0</Decimal>
					</Selection>
				</Selections>
			</Market>
			<Market>
				<Id>100413342</Id>
				<Sequence>0</Sequence>
				<TradingStatus>Closed</TradingStatus>
				<Name>Home Team Points Over/Under 73.50</Name>
				<ExpiryUtc>2016-07-06T17:00:00</ExpiryUtc>
				<Handicap>73.50</Handicap>
				<MarketType>
					<Id>8421</Id>
					<Name>Home Team Points Over/Under</Name>
					<IsHandicap>true</IsHandicap>
				</MarketType>
				<InPlay>true</InPlay>
				<Selections>
					<Selection>
						<Id>301140377</Id>
						<TradingStatus>Suspended</TradingStatus>
						<Name>Over</Name>
						<Outcome>
							<Id>30</Id>
							<Name>Over</Name>
						</Outcome>
						<Numerator>0</Numerator>
						<Denominator>1</Denominator>
						<Decimal>1.0</Decimal>
					</Selection>
					<Selection>
						<Id>301140378</Id>
						<TradingStatus>Suspended</TradingStatus>
						<Name>Under</Name>
						<Outcome>
							<Id>31</Id>
							<Name>Under</Name>
						</Outcome>
						<Numerator>0</Numerator>
						<Denominator>1</Denominator>
						<Decimal>1.0</Decimal>
					</Selection>
				</Selections>
			</Market>
		</Markets>
	</MarketSet>
</Updategram>