<?xml version="1.0" encoding="utf-8"?>
<Updategram xmlns:i="http://www.w3.org/2001/XMLSchema-instance" xmlns="http://schemas.sportsdataservices.com/integrationService/v3">
	<Header>
		<MessageGuid>08b23f13-5987-4a64-b24c-73952f02061f</MessageGuid>
		<TimeStampUtc>2016-07-06T17:27:47.5378346Z</TimeStampUtc>
		<Retry>0</Retry>
	</Header>
	<ResultSet>
		<FixtureId>4048000</FixtureId>
		<Results>
			<MarketResult>
				<MarketId>100413402</MarketId>
				<MarketSequence>0</MarketSequence>
				<Results>
					<SelectionResult>
						<SelectionId>301140497</SelectionId>
						<ResultStatus>Loser</ResultStatus>
					</SelectionResult>
					<SelectionResult>
						<SelectionId>301140498</SelectionId>
						<ResultStatus>Winner</ResultStatus>
					</SelectionResult>
				</Results>
			</MarketResult>
		</Results>
	</ResultSet>
</Updategram>