<?xml version="1.0" encoding="utf-8"?>
<Updategram xmlns:i="http://www.w3.org/2001/XMLSchema-instance" xmlns="http://schemas.sportsdataservices.com/integrationService/v3">
	<Header>
		<MessageGuid>affdce71-0b3c-4397-af51-36ca4c673050</MessageGuid>
		<TimeStampUtc>2016-07-06T17:27:47.5690836Z</TimeStampUtc>
		<Retry>0</Retry>
	</Header>
	<ResultSet>
		<FixtureId>4048000</FixtureId>
		<Results>
			<MarketResult>
				<MarketId>100413209</MarketId>
				<MarketSequence>0</MarketSequence>
				<Results>
					<SelectionResult>
						<SelectionId>301140087</SelectionId>
						<ResultStatus>Loser</ResultStatus>
					</SelectionResult>
					<SelectionResult>
						<SelectionId>301140088</SelectionId>
						<ResultStatus>Loser</ResultStatus>
					</SelectionResult>
					<SelectionResult>
						<SelectionId>301140089</SelectionId>
						<ResultStatus>Winner</ResultStatus>
					</SelectionResult>
				</Results>
			</MarketResult>
		</Results>
	</ResultSet>
</Updategram>