<?xml version="1.0" encoding="utf-8"?>
<Updategram xmlns:i="http://www.w3.org/2001/XMLSchema-instance" xmlns="http://schemas.sportsdataservices.com/integrationService/v3">
	<Header>
		<MessageGuid>b71d39be-93f6-4b36-b6bc-ade7c9a8f6b0</MessageGuid>
		<TimeStampUtc>2016-07-06T18:24:41.8504263Z</TimeStampUtc>
		<Retry>0</Retry>
	</Header>
	<ResultSet>
		<FixtureId>4048000</FixtureId>
		<Results>
			<MarketResult>
				<MarketId>100413724</MarketId>
				<MarketSequence>0</MarketSequence>
				<Results>
					<SelectionResult>
						<SelectionId>301141151</SelectionId>
						<ResultStatus>Winner</ResultStatus>
					</SelectionResult>
					<SelectionResult>
						<SelectionId>301141152</SelectionId>
						<ResultStatus>Loser</ResultStatus>
					</SelectionResult>
				</Results>
			</MarketResult>
		</Results>
	</ResultSet>
</Updategram>