{"content": "{\"FixtureId\":\"5986185\",\"CustomerId\":6426,\"StartedAtUtc\":\"2019-03-14T11:31:26.209Z\",\"FinishedAtUtc\":null,\"TeamA\":null,\"TeamB\":null,\"CurrentServer\":\"TeamA\",\"MatchScore\":{\"ScoreInSets\":{\"TeamA\":1,\"TeamB\":0},\"ScoreInPoints\":{\"TeamA\":11,\"TeamB\":6}},\"MatchStatus\":\"BetweenPoints\",\"SanctionStatus\":\"Safe\",\"IsReliable\":true,\"MessageTimestampUtc\":\"2019-03-14T12:05:20.389Z\"}", "meta": {"timestamp": "2019-03-14 12:05:20.424305", "sport": "volleyball"}, "provider": "BGIN_MD"}